{
  "sidebar": {
    "collapse": "Collapse",
    "expand": "Expand",
    "close": "Close menu"
  },
  "topbar": {
    "openMenu": "Open menu",
    "changeTheme": "Change theme",
    "theme": {
      "light": "Switch to light mode",
      "dark": "Switch to dark mode",
      "lightLabel": "Light",
      "darkLabel": "Dark"
    },
    "notifications": "Notifications",
    "changeLanguage": "Change language",
    "profile": "User profile",
    "openAccountMenu": "Open account menu",
    "account": {
      "title": "My Account",
      "profile": "Profile",
      "settings": "Settings",
      "logout": "Log out"
    },
    "lang": {
      "en": "English",
      "bh": "Bosanski"
    }
  },
  "portal": {
    "admin": {
      "badge": "ADMIN"
    },
    "employee": {
      "badge": "EMPLOYEE"
    }
  },
  "guest": {
    "backToHome": "Back to home",
    "topbar": {
      "signIn": "Sign in",
      "register": "Register company"
    },
    "footer": {
      "copyright": "© 2026 BHCOM.BA. All rights reserved.",
      "privacy": "Privacy",
      "terms": "Terms",
      "contact": "Contact"
    }
  },
  "landing": {
    "hero": {
      "title": "Logistics operations for modern fleets",
      "subtitle": "Manage shipments, fleet, and organization settings in one platform built for Bosnia and Herzegovina.",
      "ctaRegister": "Register your company",
      "ctaSignIn": "Sign in"
    },
    "features": {
      "title": "Everything you need to run logistics",
      "fleet": {
        "title": "Fleet management",
        "description": "Track vehicles, maintenance, and driver assignments from a single workspace."
      },
      "shipments": {
        "title": "Shipment tracking",
        "description": "Create, monitor, and resolve shipments with real-time operational visibility."
      },
      "admin": {
        "title": "Organization control",
        "description": "Admins configure the platform, manage users, and oversee company settings."
      }
    },
    "portals": {
      "title": "Choose your portal",
      "subtitle": "Employees and organization admins use separate sign-in portals.",
      "employee": {
        "badge": "Employee portal",
        "title": "For employees",
        "description": "Sign in to manage daily operations — shipments, fleet, orders, and reports."
      },
      "admin": {
        "badge": "Admin portal",
        "title": "For organization admins",
        "description": "Sign in to manage your company, users, and platform configuration."
      }
    }
  },
  "signIn": {
    "title": "Sign in to BHCOM",
    "subtitle": "Choose the portal that matches your role.",
    "portals": {
      "employee": {
        "badge": "Employee portal",
        "title": "Employee sign in",
        "description": "Access your workspace for shipments, fleet, and daily operations."
      },
      "admin": {
        "badge": "Admin portal",
        "title": "Admin sign in",
        "description": "Manage your organization, users, and platform settings."
      }
    }
  },
  "login": {
    "admin": {
      "badge": "Admin portal",
      "title": "Admin sign in",
      "subtitle": "Sign in to manage the platform"
    },
    "employee": {
      "badge": "Employee portal",
      "title": "Employee sign in",
      "subtitle": "Sign in to access your workspace"
    },
    "username": "Username",
    "password": "Password",
    "submit": "Sign in",
    "error": "Sign in failed. Please try again.",
    "choosePortal": "Wrong portal? Choose again",
    "createAdminAccount": "New organization? Register"
  },
  "register": {
    "admin": {
      "badge": "Admin portal",
      "title": "Create admin account",
      "subtitle": "Register your organization to manage the platform"
    },
    "signIn": "Already have an account? Sign in",
    "error": "Registration failed. Please try again.",
    "success": {
      "title": "Registration received",
      "message": "Your account is being verified. Our team will reach out shortly. Please check your email for updates."
    }
  },
  "nav": {
    "admin": {
      "sections": {
        "main": "ADMIN"
      },
      "dashboard": "Dashboard",
      "users": "Users",
      "settings": "Settings"
    },
    "sections": {
      "dashboard": "DASHBOARD",
      "shipments": "SHIPMENTS",
      "fleet": "FLEET MANAGEMENT",
      "vendorsClients": "VENDORS & CLIENTS",
      "orders": "ORDERS",
      "reports": "REPORTS"
    },
    "overview": "Overview",
    "liveMap": "Live Shipment Map",
    "fleetStatus": "Fleet Status",
    "allShipments": "All Shipments",
    "trackShipment": "Track Shipment",
    "createShipment": "Create Shipment",
    "delayedShipments": "Delayed Shipments",
    "vehicleList": "Vehicle List",
    "createVehicle": "Create Vehicle",
    "maintenanceLogs": "Maintenance Logs",
    "driverAssignments": "Driver Assignments",
    "vendorDirectory": "Vendor Directory",
    "addVendor": "Add Vendor",
    "clientsList": "Clients List",
    "clientFeedback": "Client Feedback",
    "allOrders": "All Orders",
    "scheduledDeliveries": "Scheduled Deliveries",
    "returns": "Returns",
    "cancellations": "Cancellations",
    "deliveryPerformance": "Delivery Performance",
    "revenueAnalysis": "Revenue Analysis",
    "fleetEfficiency": "Fleet Efficiency"
  },
  "pages": {
    "dashboardOverview": "Dashboard Overview",
    "liveMap": "Live Shipment Map",
    "fleetStatus": "Fleet Status",
    "allShipments": "All Shipments",
    "trackShipment": "Track Shipment",
    "createShipment": "Create Shipment",
    "delayedShipments": "Delayed Shipments",
    "vehicleList": "Vehicle List",
    "createVehicle": "Create Vehicle",
    "maintenanceLogs": "Maintenance Logs",
    "driverAssignments": "Driver Assignments",
    "vendorDirectory": "Vendor Directory",
    "addVendor": "Add Vendor",
    "clientsList": "Clients List",
    "clientFeedback": "Client Feedback",
    "allOrders": "All Orders",
    "scheduledDeliveries": "Scheduled Deliveries",
    "returns": "Returns",
    "cancellations": "Cancellations",
    "deliveryPerformance": "Delivery Performance",
    "revenueAnalysis": "Revenue Analysis",
    "fleetEfficiency": "Fleet Efficiency",
    "admin": {
      "dashboard": "Admin Dashboard",
      "users": "User Management",
      "settings": "System Settings"
    }
  },
  "tables": {
    "common": {
      "loading": "Loading...",
      "empty": "No records found.",
      "loadError": "Unable to load table data.",
      "previous": "Previous",
      "next": "Next",
      "showingSummary": "Showing {{from}} to {{to}} of {{total}} {{entity}}",
      "actions": "Row actions",
      "actionsMenu": "Actions"
    },
    "shipments": {
      "title": "Shipment List",
      "entity": "shipments",
      "columns": {
        "id": "ID",
        "customer": "Customer",
        "origin": "Origin",
        "destination": "Destination",
        "departure": "Departure",
        "eta": "ETA",
        "status": "Status",
        "type": "Type",
        "priority": "Priority"
      },
      "status": {
        "in_transit": "In Transit",
        "pending": "Pending",
        "delivered": "Delivered"
      },
      "type": {
        "road": "Road",
        "air": "Air",
        "sea": "Sea"
      },
      "priority": {
        "standard": "Standard",
        "express": "Express",
        "economy": "Economy"
      },
      "actions": {
        "view": "View Details",
        "edit": "Edit Shipment",
        "duplicate": "Duplicate",
        "delete": "Delete"
      },
      "filters": {
        "search": "Search",
        "searchPlaceholder": "Search shipments...",
        "status": "Status",
        "allStatuses": "All statuses",
        "type": "Type",
        "allTypes": "All types",
        "priority": "Priority",
        "allPriorities": "All priorities"
      }
    }
  },
  "forms": {
    "common": {
      "previous": "Previous",
      "next": "Next",
      "stepOf": "Step {{current}} of {{total}}",
      "percentComplete": "{{percent}}% Complete",
      "fieldRequired": "This field is required",
      "errors": {
        "required": "This field is required",
        "email": "Enter a valid email address",
        "minLength": "Must be at least {{min}} characters",
        "maxLength": "Must be at most {{max}} characters",
        "min": "Must be at least {{min}}",
        "max": "Must be at most {{max}}",
        "pattern": "Invalid format",
        "passwordMismatch": "Passwords do not match",
        "invalid": "This value is invalid"
      }
    },
    "createShipment": {
      "steps": {
        "type": "Shipment Type",
        "addresses": "Addresses",
        "packages": "Package Details",
        "services": "Services",
        "review": "Review"
      },
      "sections": {
        "type": {
          "title": "Shipment Type & Priority",
          "subtitle": "Select the type of shipment and delivery priority"
        },
        "origin": {
          "title": "Origin Address",
          "subtitle": "Enter the pickup location details"
        },
        "destination": {
          "title": "Destination Address",
          "subtitle": "Enter the delivery location details"
        },
        "packages": {
          "title": "Package Details",
          "subtitle": "Add items to your shipment"
        },
        "services": {
          "title": "Special Services & Options",
          "subtitle": "Configure additional services for your shipment"
        },
        "review": {
          "title": "Review & Cost Estimate",
          "subtitle": "Review your shipment details and get a cost estimate"
        }
      },
      "fields": {
        "shipmentType": "Shipment Type",
        "deliveryPriority": "Delivery Priority",
        "pickupDate": "Pickup Date",
        "deliveryDate": "Preferred Delivery Date",
        "companyName": "Company Name",
        "contactName": "Contact Name",
        "addressLine1": "Address Line 1",
        "addressLine2": "Address Line 2 (Optional)",
        "city": "City",
        "state": "State/Province",
        "zip": "ZIP/Postal Code",
        "phone": "Phone Number",
        "email": "Email Address",
        "preferredCarrier": "Preferred Carrier",
        "serviceLevel": "Service Level",
        "specialInstructions": "Special Instructions"
      },
      "placeholders": {
        "pickupDate": "Select pickup date",
        "deliveryDate": "Select delivery date",
        "companyName": "Enter company name",
        "contactName": "Enter contact name",
        "addressLine1": "Enter street address",
        "addressLine2": "Enter apartment, suite, etc.",
        "city": "Enter city",
        "state": "Select state",
        "zip": "Enter ZIP code",
        "phone": "Enter phone number",
        "email": "Enter email address",
        "selectCarrier": "Select carrier",
        "selectService": "Select service",
        "specialInstructions": "Enter any special handling instructions, delivery notes, or requirements..."
      },
      "shipmentTypes": {
        "standardPackage": "Standard Package",
        "documentEnvelope": "Document Envelope",
        "freightPallet": "Freight/Pallet",
        "bulkCargo": "Bulk Cargo"
      },
      "priority": {
        "standard": {
          "title": "Standard",
          "description": "5-7 business days",
          "price": "$15.99"
        },
        "express": {
          "title": "Express",
          "description": "2-3 business days",
          "price": "$29.99"
        },
        "overnight": {
          "title": "Overnight",
          "description": "Next business day",
          "price": "$49.99"
        }
      },
      "packages": {
        "itemLabel": "Item {{index}}",
        "description": "Description",
        "descriptionPlaceholder": "Enter item description",
        "category": "Category",
        "quantity": "Quantity",
        "weight": "Weight (lbs)",
        "value": "Value ($)",
        "hazardous": "Hazardous",
        "dimensions": "Dimensions (inches)",
        "length": "Length",
        "width": "Width",
        "height": "Height",
        "addItem": "Add Another Item",
        "totalItems": "Total Items",
        "totalWeight": "Total Weight",
        "totalValue": "Total Value",
        "weightValue": "{{weight}} lbs",
        "currencyValue": "${{value}}"
      },
      "categories": {
        "general": "General Merchandise",
        "electronics": "Electronics",
        "clothing": "Clothing",
        "food": "Food & Beverage",
        "documents": "Documents"
      },
      "carriers": {
        "fedex": "FedEx",
        "ups": "UPS",
        "dhl": "DHL",
        "usps": "USPS"
      },
      "serviceLevels": {
        "ground": "Ground",
        "express": "Express",
        "overnight": "Overnight"
      },
      "services": {
        "insuranceCoverage": "Insurance Coverage",
        "insuranceCoverageDesc": "Protect your shipment against loss or damage",
        "signatureRequired": "Signature Required",
        "signatureRequiredDesc": "Require recipient signature upon delivery",
        "fragileHandling": "Fragile Handling",
        "fragileHandlingDesc": "Extra care for delicate items",
        "temperatureControl": "Temperature Control",
        "temperatureControlDesc": "Climate-controlled transport",
        "infoBanner": "Additional services may affect shipping cost and delivery time. Review the cost estimate in the next step."
      },
      "review": {
        "summary": "Shipment Summary",
        "type": "Type",
        "priority": "Priority",
        "totalItems": "Total Items",
        "totalWeight": "Total Weight",
        "totalValue": "Total Value",
        "route": "Route",
        "from": "From",
        "to": "To",
        "services": "Special Services",
        "noServices": "No special services selected.",
        "costBreakdown": "Cost Breakdown",
        "baseShipping": "Base Shipping",
        "weightCharge": "Weight Charge",
        "servicesCharge": "Services",
        "totalCost": "Total Estimated Cost",
        "recalculate": "Recalculate Estimate",
        "estimateNote": "This is an estimate. Final cost may vary based on actual dimensions and carrier rates."
      },
      "actions": {
        "create": "Create Shipment"
      }
    },
    "createVehicle": {
      "title": "Create Vehicle",
      "steps": {
        "main": "Vehicle Details"
      },
      "sections": {
        "identity": {
          "title": "Vehicle Information",
          "subtitle": "Enter basic identification details for the vehicle"
        },
        "specs": {
          "title": "Specifications",
          "subtitle": "Configure type, capacity, and operational status"
        }
      },
      "fields": {
        "plateNumber": "License Plate",
        "make": "Make",
        "model": "Model",
        "year": "Year",
        "vehicleType": "Vehicle Type",
        "capacityKg": "Capacity (kg)",
        "status": "Status",
        "notes": "Notes"
      },
      "placeholders": {
        "plateNumber": "Enter license plate number",
        "make": "Enter manufacturer",
        "model": "Enter model name",
        "year": "e.g. 2024",
        "vehicleType": "Select vehicle type",
        "capacityKg": "Enter max load capacity",
        "status": "Select status",
        "notes": "Optional notes about the vehicle..."
      },
      "vehicleTypes": {
        "van": "Van",
        "truck": "Truck",
        "trailer": "Trailer"
      },
      "statuses": {
        "active": "Active",
        "maintenance": "In Maintenance",
        "retired": "Retired"
      },
      "actions": {
        "create": "Create Vehicle"
      }
    },
    "registerAdmin": {
      "steps": {
        "personal": "Personal details",
        "company": "Company",
        "location": "Location"
      },
      "sections": {
        "contact": {
          "title": "Contact information",
          "subtitle": "Your personal details and login credentials"
        },
        "business": {
          "title": "Company information",
          "subtitle": "Details about your organization"
        },
        "address": {
          "title": "Business address",
          "subtitle": "Where your company is located"
        }
      },
      "fields": {
        "title": "Title",
        "firstName": "First name",
        "lastName": "Last name",
        "email": "Email",
        "password": "Password",
        "passwordConfirm": "Confirm password",
        "phone": "Phone",
        "companyName": "Company name",
        "vatId": "VAT ID",
        "country": "Country",
        "city": "City",
        "postcode": "Postcode",
        "address": "Address"
      },
      "titles": {
        "mr": "Mr",
        "ms": "Ms"
      },
      "countries": {
        "BA": "Bosnia and Herzegovina",
        "RS": "Serbia",
        "HR": "Croatia",
        "ME": "Montenegro",
        "MK": "North Macedonia",
        "AL": "Albania",
        "SI": "Slovenia",
        "DE": "Germany",
        "AT": "Austria",
        "IT": "Italy",
        "FR": "France",
        "NL": "Netherlands",
        "BE": "Belgium",
        "CH": "Switzerland",
        "GB": "United Kingdom",
        "PL": "Poland",
        "CZ": "Czech Republic",
        "HU": "Hungary",
        "RO": "Romania",
        "BG": "Bulgaria",
        "GR": "Greece",
        "ES": "Spain",
        "PT": "Portugal",
        "SE": "Sweden",
        "DK": "Denmark"
      },
      "actions": {
        "submit": "Submit registration"
      }
    }
  }
}
